[
  {
    "no": "1",
    "name": "清水 典佳",
    "clinic": "日本大学歯学部附属歯科病院"
  },
  {
    "no": "2",
    "name": "居波 徹",
    "clinic": "いなみ矯正歯科"
  },
  {
    "no": "11",
    "name": "飯嶋雅弘",
    "clinic": "北海道医療大学歯学部口腔構造・機能発育学系　歯科矯正学分野"
  },
  {
    "no": "12",
    "name": "佐藤 嘉晃",
    "clinic": "北海道大学大学院歯学研究院歯科矯正学教室"
  },
  {
    "no": "13",
    "name": "佐藤和朗",
    "clinic": "岩手医科大学歯学部口腔保健育成学講座 歯科矯正学分野"
  },
  {
    "no": "14",
    "name": "北浦英樹",
    "clinic": "東北大学大学院歯学研究科顎口腔矯正学分野"
  },
  {
    "no": "15",
    "name": "五十嵐薫",
    "clinic": "東北大学大学院歯学研究科頭蓋顔面先天異常学分野"
  },
  {
    "no": "16",
    "name": "川鍋仁",
    "clinic": "奥羽大学歯学部成長発育歯学講座歯科矯正学分野"
  },
  {
    "no": "17",
    "name": "丹原惇",
    "clinic": "新潟大学大学院 医歯学総合研究科 歯科矯正学分野"
  },
  {
    "no": "18",
    "name": "小林さくら子",
    "clinic": "日本歯科大学新潟生命歯学部歯科矯正学講座"
  },
  {
    "no": "19",
    "name": "影山徹",
    "clinic": "松本歯科大学病院育成期口腔診療部門矯正歯科"
  },
  {
    "no": "20",
    "name": "須田直人",
    "clinic": "明海大学歯学部 形態機能成育学講座 歯科矯正学分野"
  },
  {
    "no": "21",
    "name": "根岸慎一",
    "clinic": "日本大学松戸歯学部歯科矯正学講座"
  },
  {
    "no": "22",
    "name": "小野卓史",
    "clinic": "東京科学大学大学院医歯学総合研究科 咬合機能矯正学分野"
  },
  {
    "no": "23",
    "name": "森山啓司",
    "clinic": "東京科学大学大学院医歯学総合研究科 顎顔面矯正学分野"
  },
  {
    "no": "24",
    "name": "西井 康",
    "clinic": "東京歯科大学歯科矯正学講座"
  },
  {
    "no": "25",
    "name": "新井一仁",
    "clinic": "日本歯科大学生命歯学部 歯科矯正学講座"
  },
  {
    "no": "26",
    "name": "本吉満",
    "clinic": "日本大学歯学部 歯科矯正学講座"
  },
  {
    "no": "27",
    "name": "中納治久",
    "clinic": "昭和大学歯学部歯科矯正学講座"
  },
  {
    "no": "28",
    "name": "友成博",
    "clinic": "鶴見大学歯学部歯科矯正学講座"
  },
  {
    "no": "29",
    "name": "山口徹太郎",
    "clinic": "神奈川歯科大学大学院口腔統合医療学講座歯科矯正学分野"
  },
  {
    "no": "30",
    "name": "宮澤健",
    "clinic": "愛知学院大学歯学部歯科矯正学講座"
  },
  {
    "no": "31",
    "name": "北井則行",
    "clinic": "朝日大学歯学部 口腔構造機能発育学講座 歯科矯正学分野"
  },
  {
    "no": "32",
    "name": "山城隆",
    "clinic": "大阪大学大学院 歯学研究科 顎顔面口腔矯正学教室"
  },
  {
    "no": "33",
    "name": "西浦亜紀",
    "clinic": "大阪歯科大学附属病院矯正歯科"
  },
  {
    "no": "34",
    "name": "上岡寛",
    "clinic": "岡山大学大学院医歯薬学総合研究科歯科矯正学分野"
  },
  {
    "no": "35",
    "name": "谷本幸太郎",
    "clinic": "広島大学大学院医歯薬保健学研究科応用生命科学部門（歯科矯正学）"
  },
  {
    "no": "36",
    "name": "田中栄二",
    "clinic": "徳島大学大学院医歯薬学研究部 口腔顎顔面矯正学分野"
  },
  {
    "no": "37",
    "name": "川元龍夫",
    "clinic": "九州歯科大学歯学部顎口腔機能矯正学分野"
  },
  {
    "no": "38",
    "name": "高橋一郎",
    "clinic": "九州大学大学院歯学研究院 口腔保健推進学講座 歯科矯正学分野"
  },
  {
    "no": "39",
    "name": "玉置幸雄",
    "clinic": "福岡歯科大学成長発達歯学講座矯正歯科学分野"
  },
  {
    "no": "40",
    "name": "宮脇正一",
    "clinic": "鹿児島大学大学院 医歯学総合研究科 歯科矯正学分野（矯正歯科）"
  },
  {
    "no": "101",
    "name": "小澤 浩之",
    "clinic": "洗足スクエア歯科医院矯正歯科"
  },
  {
    "no": "102",
    "name": "嘉ノ海 龍三",
    "clinic": "カノミ矯正歯科クリニック"
  },
  {
    "no": "103",
    "name": "近藤 成智",
    "clinic": "こんどう矯正歯科"
  },
  {
    "no": "104",
    "name": "下田 哲也",
    "clinic": "しもだ矯正歯科クリニック"
  },
  {
    "no": "105",
    "name": "大塚 亮",
    "clinic": "ファミリア歯科矯正"
  },
  {
    "no": "106",
    "name": "大坪 邦彦",
    "clinic": "大坪矯正歯科医院"
  },
  {
    "no": "107",
    "name": "永田 裕保",
    "clinic": "永田矯正歯科"
  },
  {
    "no": "108",
    "name": "野村 泰世",
    "clinic": "のむら矯正歯科"
  },
  {
    "no": "109",
    "name": "井上 則子",
    "clinic": "新札幌アン矯正歯科クリニック"
  },
  {
    "no": "110",
    "name": "髙橋 一朗",
    "clinic": "西大寺髙橋矯正歯科"
  },
  {
    "no": "111",
    "name": "田口 元康",
    "clinic": "北千住矯正歯科"
  },
  {
    "no": "112",
    "name": "深井 統久",
    "clinic": "深井矯正歯科クリニック"
  },
  {
    "no": "113",
    "name": "髙木 伸治",
    "clinic": "スマイル矯正歯科"
  },
  {
    "no": "114",
    "name": "藤山 光治",
    "clinic": "ふじやま矯正歯科"
  },
  {
    "no": "115",
    "name": "尾崎 周作",
    "clinic": "尾崎矯正歯科クリニック"
  },
  {
    "no": "116",
    "name": "秋山 真人",
    "clinic": "ひたちの矯正歯科医院"
  },
  {
    "no": "117",
    "name": "中本 清嗣",
    "clinic": "中本矯正歯科"
  },
  {
    "no": "118",
    "name": "田渕 雅子",
    "clinic": "愛知学院大学歯学部 附属病院矯正歯科"
  },
  {
    "no": "119",
    "name": "布川 隆三",
    "clinic": "布川矯正歯科"
  },
  {
    "no": "120",
    "name": "松野 功",
    "clinic": "赤坂まつの矯正歯科"
  },
  {
    "no": "121",
    "name": "鶴田 仁史",
    "clinic": "広島中央矯正歯科"
  },
  {
    "no": "122",
    "name": "高木 豊明",
    "clinic": "矯正歯科たかぎ・クリニック"
  },
  {
    "no": "123",
    "name": "三村 博",
    "clinic": "みむら矯正歯科"
  },
  {
    "no": "124",
    "name": "北澤 愼一",
    "clinic": "きたざわ矯正歯科"
  },
  {
    "no": "125",
    "name": "濵嵜 広二朗",
    "clinic": "はまさき矯正歯科医院"
  },
  {
    "no": "126",
    "name": "岡 健治",
    "clinic": "岡矯正歯科"
  },
  {
    "no": "127",
    "name": "山下 和夫",
    "clinic": "駅前矯正歯科"
  },
  {
    "no": "128",
    "name": "山田 秀樹",
    "clinic": "歯科矯正 ちどり歯科医院"
  },
  {
    "no": "129",
    "name": "松浦 輝雄",
    "clinic": "まつうら矯正歯科医院"
  },
  {
    "no": "130",
    "name": "飯島 重樹",
    "clinic": "いいじま矯正歯科"
  },
  {
    "no": "131",
    "name": "吉野 成史",
    "clinic": "吉野矯正歯科"
  },
  {
    "no": "132",
    "name": "小坂竜也",
    "clinic": "小坂矯正歯科"
  },
  {
    "no": "133",
    "name": "内田慎也",
    "clinic": "内田矯正歯科クリニック"
  },
  {
    "no": "134",
    "name": "三崎浩一",
    "clinic": "クリオネ矯正歯科"
  },
  {
    "no": "135",
    "name": "鮎瀬節子",
    "clinic": "あいがせ矯正歯科"
  },
  {
    "no": "136",
    "name": "鈴木巌",
    "clinic": "すずき矯正歯科"
  },
  {
    "no": "137",
    "name": "小幡明彦",
    "clinic": "おばた矯正歯科クリニック"
  },
  {
    "no": "138",
    "name": "堀井和宏",
    "clinic": "ほりい矯正歯科クリニック"
  },
  {
    "no": "139",
    "name": "上野拓郎",
    "clinic": "E-line矯正歯科"
  },
  {
    "no": "140",
    "name": "近川美喜子",
    "clinic": "近川矯正歯科クリニック"
  },
  {
    "no": "141",
    "name": "野村真弓",
    "clinic": "髙根病院　歯科"
  },
  {
    "no": "142",
    "name": "北村裕",
    "clinic": "洋光台矯正歯科"
  },
  {
    "no": "143",
    "name": "切通正智",
    "clinic": "きり矯正歯科クリニック"
  },
  {
    "no": "144",
    "name": "犬束信一",
    "clinic": "いぬづか矯正歯科"
  },
  {
    "no": "145",
    "name": "月星千恵",
    "clinic": "月星歯科クリニック"
  },
  {
    "no": "146",
    "name": "山田一尋",
    "clinic": "あすなろ小児歯科医院矯正歯科"
  },
  {
    "no": "147",
    "name": "平木建史",
    "clinic": "ひらき矯正歯科"
  },
  {
    "no": "148",
    "name": "久保田雅人",
    "clinic": "アリビオ矯正歯科クリニック"
  },
  {
    "no": "149",
    "name": "奥橋園子",
    "clinic": "そのこ矯正歯科"
  },
  {
    "no": "150",
    "name": "村上道雄",
    "clinic": "村上矯正歯科クリニック"
  },
  {
    "no": "151",
    "name": "小川晴也",
    "clinic": "小川矯正歯科"
  },
  {
    "no": "152",
    "name": "石井一裕",
    "clinic": "矯正歯科石井クリニック"
  },
  {
    "no": "153",
    "name": "足立敏",
    "clinic": "足立矯正歯科"
  },
  {
    "no": "154",
    "name": "小川聖美",
    "clinic": "小川矯正歯科"
  },
  {
    "no": "155",
    "name": "日高修",
    "clinic": "ひだか矯正歯科クリニック"
  },
  {
    "no": "156",
    "name": "高橋啓",
    "clinic": "高橋矯正歯科クリニック"
  },
  {
    "no": "157",
    "name": "串本一男",
    "clinic": "クシモト矯正歯科"
  },
  {
    "no": "158",
    "name": "早川進一",
    "clinic": "はやかわ矯正歯科"
  },
  {
    "no": "159",
    "name": "今城広治",
    "clinic": "いまじょう矯正歯科クリニック"
  },
  {
    "no": "160",
    "name": "郷義明",
    "clinic": "ごう矯正歯科"
  },
  {
    "no": "161",
    "name": "杉山晶二",
    "clinic": "杉山矯正歯科"
  },
  {
    "no": "162",
    "name": "宮﨑顕道",
    "clinic": "みやざき矯正歯科"
  },
  {
    "no": "163",
    "name": "平野武弘",
    "clinic": "ひらの矯正歯科クリニック"
  },
  {
    "no": "164",
    "name": "荻野茂",
    "clinic": "おぎの矯正歯科"
  },
  {
    "no": "165",
    "name": "箕浦雄介",
    "clinic": "王子みのうら矯正歯科"
  },
  {
    "no": "166",
    "name": "新井茂",
    "clinic": "新井矯正歯科"
  },
  {
    "no": "167",
    "name": "岡崎恵一郎",
    "clinic": "おかざき矯正歯科クリニック"
  },
  {
    "no": "168",
    "name": "桜田明宏",
    "clinic": "さっぽろ矯正歯科クリニック"
  },
  {
    "no": "169",
    "name": "河上宗博",
    "clinic": "麻生矯正歯科"
  },
  {
    "no": "170",
    "name": "上木康文",
    "clinic": "うえき矯正歯科クリニック"
  },
  {
    "no": "171",
    "name": "澤秀一郎",
    "clinic": "沢矯正歯科医院"
  },
  {
    "no": "172",
    "name": "大塚重雄",
    "clinic": "大塚矯正歯科"
  },
  {
    "no": "173",
    "name": "阿部操",
    "clinic": "齋藤歯科クリニック"
  },
  {
    "no": "174",
    "name": "佐藤俊仁",
    "clinic": "さとう矯正歯科"
  },
  {
    "no": "175",
    "name": "山田尋士",
    "clinic": "ヤマダ矯正歯科"
  },
  {
    "no": "176",
    "name": "橋場千織",
    "clinic": "はしば矯正歯科"
  },
  {
    "no": "177",
    "name": "中島祥博",
    "clinic": "ナカジマ矯正歯科クリニック"
  },
  {
    "no": "178",
    "name": "田村隆彦",
    "clinic": "日本大学歯学部附属歯科病院　歯科矯正科"
  },
  {
    "no": "179",
    "name": "土門明哉",
    "clinic": "ドモン矯正歯科"
  },
  {
    "no": "180",
    "name": "黒田勝也",
    "clinic": "クロダ矯正歯科"
  },
  {
    "no": "181",
    "name": "岸本正雄",
    "clinic": "きしもと矯正歯科クリニック"
  },
  {
    "no": "182",
    "name": "臼井暁昭",
    "clinic": "あかつき矯正歯科クリニック"
  },
  {
    "no": "183",
    "name": "高大松",
    "clinic": "大松矯正歯科クリニック"
  },
  {
    "no": "184",
    "name": "松原進",
    "clinic": "松原矯正歯科クリニック"
  },
  {
    "no": "185",
    "name": "西田真",
    "clinic": "西田矯正歯科"
  },
  {
    "no": "186",
    "name": "大岩逸朗",
    "clinic": "大岩矯正歯科トバ"
  },
  {
    "no": "187",
    "name": "廣俊明",
    "clinic": "ひろ矯正歯科"
  },
  {
    "no": "188",
    "name": "金子知生",
    "clinic": "北海道病院歯科診療センター咬合系歯科矯正科"
  },
  {
    "no": "189",
    "name": "青木泰樹",
    "clinic": "オレフィス矯正歯科"
  },
  {
    "no": "190",
    "name": "白井英俊",
    "clinic": "シライ矯正歯科クリニック"
  },
  {
    "no": "191",
    "name": "平久忠輝",
    "clinic": "東戸塚たいらく矯正歯科"
  },
  {
    "no": "192",
    "name": "土持正",
    "clinic": "土持矯正歯科医院"
  },
  {
    "no": "193",
    "name": "星隆夫",
    "clinic": "星歯科矯正"
  },
  {
    "no": "194",
    "name": "川村全",
    "clinic": "川村矯正歯科"
  },
  {
    "no": "195",
    "name": "石渡靖夫",
    "clinic": "いしわた矯正歯科"
  },
  {
    "no": "196",
    "name": "蔵真由美",
    "clinic": "クラ矯正歯科クリニック"
  },
  {
    "no": "197",
    "name": "渡辺和也",
    "clinic": "渡辺矯正歯科"
  },
  {
    "no": "198",
    "name": "中澤真紀",
    "clinic": "スマイル矯正歯科"
  },
  {
    "no": "199",
    "name": "萬　建一",
    "clinic": "よろず矯正歯科クリニック"
  },
  {
    "no": "200",
    "name": "中村理枝",
    "clinic": "なかむら矯正歯科"
  },
  {
    "no": "201",
    "name": "川村雅俊",
    "clinic": "川村矯正歯科"
  },
  {
    "no": "202",
    "name": "野呂卓司",
    "clinic": "野呂矯正歯科"
  },
  {
    "no": "203",
    "name": "和島武毅",
    "clinic": "歯ならび矯正歯科医院"
  },
  {
    "no": "204",
    "name": "長谷川正文",
    "clinic": "長谷川矯正歯科クリニック"
  },
  {
    "no": "205",
    "name": "横川早苗",
    "clinic": "横川矯正歯科"
  },
  {
    "no": "206",
    "name": "中村順一",
    "clinic": "なかむら矯正歯科医院"
  },
  {
    "no": "207",
    "name": "藤田幸弘",
    "clinic": "藤田矯正歯科"
  },
  {
    "no": "208",
    "name": "関康弘",
    "clinic": "せき矯正歯科医院"
  },
  {
    "no": "209",
    "name": "廣島邦泰",
    "clinic": "アイウエオ矯正歯科医院"
  },
  {
    "no": "210",
    "name": "府川俊彦",
    "clinic": "フカワ矯正歯科医院"
  },
  {
    "no": "211",
    "name": "松井成幸",
    "clinic": "松井矯正歯科クリニック"
  },
  {
    "no": "212",
    "name": "渡木澄子",
    "clinic": "とねき矯正歯科医院"
  },
  {
    "no": "213",
    "name": "中野廣一",
    "clinic": "なかの矯正歯科"
  },
  {
    "no": "214",
    "name": "槇宏太郎",
    "clinic": "昭和大学病院"
  },
  {
    "no": "215",
    "name": "岩崎利員",
    "clinic": "岩崎矯正歯科"
  },
  {
    "no": "216",
    "name": "鬼久保平",
    "clinic": "おにくぼ矯正歯科"
  },
  {
    "no": "217",
    "name": "大内仁守",
    "clinic": "おおうち矯正歯科小児歯科クリニック"
  },
  {
    "no": "218",
    "name": "中村桂子",
    "clinic": "スマイル矯正歯科"
  },
  {
    "no": "219",
    "name": "仁木俊雄",
    "clinic": "中村歯科医院"
  },
  {
    "no": "220",
    "name": "井上裕子",
    "clinic": "イノウエ矯正歯科"
  },
  {
    "no": "221",
    "name": "永井宏人",
    "clinic": "永井矯正歯科医院"
  },
  {
    "no": "222",
    "name": "野田修司",
    "clinic": "野田矯正歯科医院"
  },
  {
    "no": "223",
    "name": "松本淳",
    "clinic": "すぎた矯正・小児歯科"
  },
  {
    "no": "224",
    "name": "齋藤康雄",
    "clinic": "さいとう矯正歯科医院"
  },
  {
    "no": "225",
    "name": "宮崎孝明",
    "clinic": "みやざき矯正歯科医院"
  },
  {
    "no": "226",
    "name": "山本一宏",
    "clinic": "ｶﾏｸﾗﾃﾞﾝﾄﾌｪｲｼｬﾙｵｰｿﾋﾟﾃﾞｨｸｽ・山本歯科・矯正"
  },
  {
    "no": "227",
    "name": "荻原祐二",
    "clinic": "武蔵小杉矯正歯科"
  },
  {
    "no": "228",
    "name": "加藤嘉之",
    "clinic": "矯正歯科加藤歯科医院"
  },
  {
    "no": "229",
    "name": "田中千元",
    "clinic": "田中矯正歯科"
  },
  {
    "no": "230",
    "name": "渡辺洋一",
    "clinic": "渡辺矯正歯科クリニック"
  },
  {
    "no": "231",
    "name": "大川覚",
    "clinic": "大川矯正歯科クリニック"
  },
  {
    "no": "232",
    "name": "鎌田正毅",
    "clinic": "鎌田歯科矯正クリニック"
  },
  {
    "no": "233",
    "name": "富永雪穂",
    "clinic": "アルファ矯正歯科クリニック"
  },
  {
    "no": "234",
    "name": "伊藤智恵",
    "clinic": "伊藤矯正歯科クリニック"
  },
  {
    "no": "235",
    "name": "中橋章泰",
    "clinic": "なかはし矯正歯科"
  },
  {
    "no": "236",
    "name": "中川学",
    "clinic": "中川矯正歯科医院"
  },
  {
    "no": "237",
    "name": "永山純一郎",
    "clinic": "ながやま矯正歯科クリニック"
  },
  {
    "no": "238",
    "name": "和田昌久",
    "clinic": "和田矯正歯科"
  },
  {
    "no": "239",
    "name": "神崎寛人",
    "clinic": "こうざき歯科矯正クリニック"
  },
  {
    "no": "240",
    "name": "横関雅彦",
    "clinic": "横関矯正歯科クリニック"
  },
  {
    "no": "241",
    "name": "稲毛滋自",
    "clinic": "いなげ矯正歯科医院"
  },
  {
    "no": "242",
    "name": "飯野祥一朗",
    "clinic": "イーノ矯正歯科クリニック"
  },
  {
    "no": "243",
    "name": "稲見佳大",
    "clinic": "いなみ矯正歯科医院"
  },
  {
    "no": "244",
    "name": "桑原聡",
    "clinic": "くわはら矯正歯科医院"
  },
  {
    "no": "245",
    "name": "広瀬豊",
    "clinic": "広瀬矯正歯科"
  },
  {
    "no": "246",
    "name": "山田哲郎",
    "clinic": "やまだ矯正歯科クリニック"
  },
  {
    "no": "247",
    "name": "分山英次",
    "clinic": "分山矯正歯科クリニック"
  },
  {
    "no": "248",
    "name": "守本優子",
    "clinic": "もりもと矯正歯科"
  },
  {
    "no": "249",
    "name": "齋藤卓麻",
    "clinic": "さいとう矯正歯科"
  },
  {
    "no": "250",
    "name": "田中進平",
    "clinic": "金山矯正歯科クリニック"
  },
  {
    "no": "251",
    "name": "佐藤英彦",
    "clinic": "サトウ・ヤスナガ矯正歯科"
  },
  {
    "no": "252",
    "name": "野間秀郎",
    "clinic": "アルファ矯正歯科"
  },
  {
    "no": "253",
    "name": "砂原佳子",
    "clinic": "ブライト矯正歯科"
  },
  {
    "no": "254",
    "name": "菅沼與明",
    "clinic": "菅沼矯正歯科"
  },
  {
    "no": "255",
    "name": "中西洋介",
    "clinic": "中西矯正歯科"
  },
  {
    "no": "256",
    "name": "池森由幸",
    "clinic": "いけもり矯正歯科"
  },
  {
    "no": "257",
    "name": "宮本敬次郎",
    "clinic": "宮本矯正歯科医院"
  },
  {
    "no": "258",
    "name": "片岡護",
    "clinic": "かたおか矯正歯科医院"
  },
  {
    "no": "259",
    "name": "新澤牧子",
    "clinic": "しんざわ矯正歯科クリニック"
  },
  {
    "no": "260",
    "name": "舩木純三",
    "clinic": "ふなき矯正歯科"
  },
  {
    "no": "261",
    "name": "深沢裕文",
    "clinic": "ふかさわ矯正歯科クリニック"
  },
  {
    "no": "262",
    "name": "筒井照子",
    "clinic": "筒井歯科・矯正歯科医院"
  },
  {
    "no": "263",
    "name": "川端庄一郎",
    "clinic": "かわばた矯正歯科"
  },
  {
    "no": "264",
    "name": "京面伺吾",
    "clinic": "きょうめん矯正歯科"
  },
  {
    "no": "265",
    "name": "横山一徳",
    "clinic": "よこやま矯正歯科"
  },
  {
    "no": "266",
    "name": "五十嵐一吉",
    "clinic": "いがらし矯正歯科クリニック"
  },
  {
    "no": "267",
    "name": "北園俊司",
    "clinic": "きたぞの歯科矯正"
  },
  {
    "no": "268",
    "name": "堀正裕",
    "clinic": "なかむらばしデンタルクリニック"
  },
  {
    "no": "269",
    "name": "斉宮康寛",
    "clinic": "神宮前矯正歯科"
  }
]